hearthstone_builder/__init__.py
hearthstone_builder/endpoint.py
hearthstone_builder/hearthstone_query_builder.py
hearthstone_builder/query.py
hearthstone_functions/__init__.py
hearthstone_functions/dto.py
hearthstone_functions/repositorie.py
hearthstone_lab10-0.1.dist-info/METADATA
hearthstone_lab10-0.1.dist-info/WHEEL
hearthstone_lab10-0.1.dist-info/top_level.txt
hearthstone_lab10-0.1.dist-info/RECORD
