Metadata-Version: 2.1
Name: hearthstone-lab10
Version: 0.1
Summary: lab10 hearthstone
Author: Mikołaj Pastuszek
Requires-Dist: enum
Requires-Dist: requests
Requires-Dist: typing
